littlebird/__init__.py
littlebird/constants.py
littlebird/tweet_tokenizer.py
littlebird/tweet_utils.py
littlebird/scripts/__init__.py
littlebird/scripts/add_tweet_url_titles.py
littlebird_twitter_utils-1.0.0.dist-info/LICENSE
littlebird_twitter_utils-1.0.0.dist-info/METADATA
littlebird_twitter_utils-1.0.0.dist-info/WHEEL
littlebird_twitter_utils-1.0.0.dist-info/top_level.txt
littlebird_twitter_utils-1.0.0.dist-info/RECORD
