Metadata-Version: 2.1
Name: littlebird-twitter-utils
Version: 1.0.0
Summary: Utilities for reading, writing, and processing tweets
Home-page: https://github.com/AADeLucia/littlebird
Author: Alexandra DeLucia
Author-email: aadelucia@jhu.edu
License: MIT
Classifier: Programming Language :: Python :: 3
Classifier: License :: OSI Approved :: MIT License
Classifier: Operating System :: OS Independent
Requires-Python: >=3.6
License-File: LICENSE
Requires-Dist: jsonlines
Requires-Dist: regex
Requires-Dist: filetype
Requires-Dist: lxml
Requires-Dist: emoji
Requires-Dist: nltk
